cred_retrieve/__init__.py
cred_retrieve/factory.py
cred_retrieve/provider.py
cred_retrieve/providers/dotenv.py
cred_retrieve/providers/keepassxc.py
cred_retrieve/providers/keepassxc_mac.py
cred_retrieve/providers/keepassxc_win.py
cred_retrieve-0.1.3.dist-info/LICENSE
cred_retrieve-0.1.3.dist-info/METADATA
cred_retrieve-0.1.3.dist-info/WHEEL
cred_retrieve-0.1.3.dist-info/RECORD
