Metadata-Version: 2.1
Name: cred_retrieve
Version: 0.1.3
Summary: A Python package that provides a flexible way to retrieve credentials from various sources, including KeePassXC and custom credential providers.
Home-page: https://github.com/th-yoo/cred_retrieve
License: MIT
Keywords: secrets,credential,password,password storage,KeePassXC,dotenv
Author: th yoo
Author-email: taihyungyoo@gmail.com
Requires-Python: >=3.9,<4.0
Classifier: License :: OSI Approved :: MIT License
Classifier: Programming Language :: Python :: 3
Classifier: Programming Language :: Python :: 3.9
Classifier: Programming Language :: Python :: 3.10
Classifier: Programming Language :: Python :: 3.11
Classifier: Programming Language :: Python :: 3.12
Requires-Dist: reg-query (>=0.1.1,<0.2.0) ; sys_platform == "win32"
